archcraftsman/__init__.py
archcraftsman/__main__.py
archcraftsman/arguments.py
archcraftsman/autopart.py
archcraftsman/base.py
archcraftsman/basesetup.py
archcraftsman/btrfs.py
archcraftsman/config.py
archcraftsman/disk.py
archcraftsman/i18n.py
archcraftsman/imessages.py
archcraftsman/info.py
archcraftsman/installer.py
archcraftsman/manualpart.py
archcraftsman/options.py
archcraftsman/packages.py
archcraftsman/partition.py
archcraftsman/partitioninginfo.py
archcraftsman/prelaunchinfo.py
archcraftsman/shell.py
archcraftsman/systeminfo.py
archcraftsman/utils.py
archcraftsman/bundles/__init__.py
archcraftsman/bundles/bundle.py
archcraftsman/bundles/genericbundle.py
archcraftsman/bundles/gnome.py
archcraftsman/bundles/grub.py
archcraftsman/bundles/iwd.py
archcraftsman/bundles/linux.py
archcraftsman/bundles/microcodes.py
archcraftsman/bundles/networkmanager.py
archcraftsman/bundles/plasma.py
archcraftsman/bundles/systemdnet.py
archcraftsman/bundles/utils.py
archcraftsman/bundles/xfce.py
archcraftsman/bundles/generic/__init__.py
archcraftsman/bundles/shell/__init__.py
archcraftsman/bundles/shell/generateconfig.py
archcraftsman/bundles/shell/yay.py
archcraftsman/bundles/simple/__init__.py
archcraftsman/bundles/simple/architect.py
archcraftsman/bundles/simple/copyacm.py
archcraftsman/bundles/simple/grmlzsh.py
archcraftsman/bundles/simple/nvidia.py
archcraftsman/bundles/simple/terminus.py
archcraftsman/bundles/simple/zram.py
archcraftsman/locales/__init__.py
archcraftsman/locales/french.po
archcraftsman/test/__init__.py
archcraftsman/test/test_base.py
archcraftsman/test/test_utils.py
archcraftsman-4.3.2.dist-info/LICENSE.txt
archcraftsman-4.3.2.dist-info/METADATA
archcraftsman-4.3.2.dist-info/NOTICES
archcraftsman-4.3.2.dist-info/WHEEL
archcraftsman-4.3.2.dist-info/entry_points.txt
archcraftsman-4.3.2.dist-info/top_level.txt
archcraftsman-4.3.2.dist-info/RECORD
