Metadata-Version: 2.1
Name: archcraftsman
Version: 4.3.2
Summary: The careful yet very fast Arch Linux Craftsman ensuring minimal user interactions.
Home-page: https://github.com/Rawleenc/ArchCraftsman
Author: Rawleenc
License: GPL-3.0
Project-URL: Bug Tracker, https://github.com/Rawleenc/ArchCraftsman/issues
Keywords: linux,fast,installer,script,archlinux,quickstart,archcraftsman
Classifier: Programming Language :: Python :: 3.11
Requires-Python: >=3.11
License-File: LICENSE.txt
License-File: NOTICES
